vertexarray/__init__.py
vertexarray/classes.py
vertexarray-0.1.0.dist-info/DESCRIPTION.rst
vertexarray-0.1.0.dist-info/METADATA
vertexarray-0.1.0.dist-info/metadata.json
vertexarray-0.1.0.dist-info/RECORD
vertexarray-0.1.0.dist-info/top_level.txt
vertexarray-0.1.0.dist-info/WHEEL
