Metadata-Version: 2.0
Name: vertexarray
Version: 0.1.0
Summary: Simple vertex array that avoids repeating vertices
Home-page: https://github.com/kcsaff/vertexarray
Author: K.C.Saff
Author-email: kc@saff.net
License: MIT
Platform: UNKNOWN
Classifier: License :: OSI Approved :: MIT License
Classifier: Intended Audience :: Other Audience
Classifier: Programming Language :: Python :: 3
